pycacheable/__init__.py
pycacheable/backend_memory.py
pycacheable/backend_sqlite.py
pycacheable/cache_base.py
pycacheable/cacheable.py
pycacheable/hashing.py
pycacheable-0.1.2.dist-info/licenses/LICENSE
pycacheable-0.1.2.dist-info/METADATA
pycacheable-0.1.2.dist-info/WHEEL
pycacheable-0.1.2.dist-info/top_level.txt
pycacheable-0.1.2.dist-info/RECORD
