Metadata-Version: 2.4
Name: pycacheable
Version: 0.1.2
Summary: Decorator de cache para funções e métodos Python, com backends InMemory e SQLite, TTL configurável e hash estável de parâmetros.
Author-email: Leonardo Pinho <contato@leonardopinho.com>
License: MIT License
Project-URL: Homepage, https://github.com/leonardopinho/pycacheable
Project-URL: Repository, https://github.com/leonardopinho/pycacheable
Project-URL: Issues, https://github.com/leonardopinho/pycacheable/issues
Keywords: cache,decorator,sqlite,python,performance,memoization,pycharm
Classifier: Development Status :: 4 - Beta
Classifier: Intended Audience :: Developers
Classifier: License :: OSI Approved :: MIT License
Classifier: Programming Language :: Python :: 3
Classifier: Programming Language :: Python :: 3.9
Classifier: Programming Language :: Python :: 3.10
Classifier: Programming Language :: Python :: 3.11
Classifier: Programming Language :: Python :: 3.12
Classifier: Topic :: Software Development :: Libraries
Classifier: Topic :: Software Development :: Libraries :: Python Modules
Classifier: Operating System :: OS Independent
Requires-Python: >=3.9
License-File: LICENSE
Requires-Dist: typing-extensions>=4.0.0
Dynamic: license-file
